usps_tracking_tool/__init__.py
usps_tracking_tool/config.json
usps_tracking_tool/tracking.py
usps_tracking_tool-1.0.1.dist-info/LICENSE
usps_tracking_tool-1.0.1.dist-info/METADATA
usps_tracking_tool-1.0.1.dist-info/WHEEL
usps_tracking_tool-1.0.1.dist-info/entry_points.txt
usps_tracking_tool-1.0.1.dist-info/top_level.txt
usps_tracking_tool-1.0.1.dist-info/RECORD
