Metadata-Version: 2.1
Name: usps-tracking-tool
Version: 1.0.1
Summary: Command line utility to track your packages using the USPS Track Request API.
Home-page: https://github.com/LiterallyLarry/USPS-Tracking-Python
Author: Larry Hui
Author-email: larryhui@outlook.com
License: MIT
Project-URL: Bug Tracker, https://github.com/LiterallyLarry/USPS-Tracking-Python/issues
Platform: UNKNOWN
Classifier: License :: OSI Approved :: MIT License
Classifier: Operating System :: OS Independent
Classifier: Programming Language :: Python :: 3
Classifier: Programming Language :: Python :: 3.5
Classifier: Programming Language :: Python :: 3.6
Classifier: Programming Language :: Python :: 3.7
Requires-Python: >=3.4
